retexture/__init__.py
retexture/run.py
retexture-0.1.1.dist-info/LICENSE
retexture-0.1.1.dist-info/METADATA
retexture-0.1.1.dist-info/WHEEL
retexture-0.1.1.dist-info/entry_points.txt
retexture-0.1.1.dist-info/top_level.txt
retexture-0.1.1.dist-info/RECORD
