Metadata-Version: 2.1
Name: retexture
Version: 0.1.1
Summary: ReTexture dataset toolkit for generation and analysis
Home-page: https://github.com/mhyatt000/retexture
Author: Matt Hyatt
Author-email: Matthew Hyatt <mhyatt000@gmail.com>
License: MIT License
Project-URL: Homepage, https://github.com/mhyatt000/retexture
Classifier: Programming Language :: Python :: 3
Classifier: License :: OSI Approved :: MIT License
Classifier: Operating System :: OS Independent
Requires-Python: >=3.9
License-File: LICENSE
Requires-Dist: tqdm >=4.61.2
Requires-Dist: numpy >=1.23.5
Requires-Dist: hydra-core >=1.3
